Metadata-Version: 2.1
Name: dolibs
Version: 0.6.0
Summary: Library for importing ERA5 Copernicus data into Drought Observatory platform
Home-page: https://github.com/n3tmaster/ERA5_procedures
Author: Leandro Rocchi - CNR
Author-email: leandro.rocchi@cnr.it
License: MIT
Requires-Dist: cdsapi
Requires-Dist: scipy
Requires-Dist: netcdf4
Requires-Dist: rioxarray
Requires-Dist: numpy
Requires-Dist: xarray
Requires-Dist: sqlalchemy
Requires-Dist: psycopg2-binary
